[{"type":"error","inputs":[{"name":"owner","type":"address","baseType":"address","components":null,"arrayLength":null,"arrayChildren":null}],"name":"OwnableInvalidOwner"},{"type":"error","inputs":[{"name":"account","type":"address","baseType":"address","components":null,"arrayLength":null,"arrayChildren":null}],"name":"OwnableUnauthorizedAccount"},{"type":"event","inputs":[{"name":"_user","type":"address","baseType":"address","indexed":false,"components":null,"arrayLength":null,"arrayChildren":null}],"name":"Burn","anonymous":false},{"type":"event","inputs":[{"name":"_user","type":"address","baseType":"address","indexed":false,"components":null,"arrayLength":null,"arrayChildren":null}],"name":"Mint","anonymous":false},{"type":"event","inputs":[{"name":"previousOwner","type":"address","baseType":"address","indexed":true,"components":null,"arrayLength":null,"arrayChildren":null},{"name":"newOwner","type":"address","baseType":"address","indexed":true,"components":null,"arrayLength":null,"arrayChildren":null}],"name":"OwnershipTransferred","anonymous":false},{"type":"event","inputs":[{"name":"_profiler","type":"address","baseType":"address","indexed":false,"components":null,"arrayLength":null,"arrayChildren":null},{"name":"_user","type":"address","baseType":"address","indexed":false,"components":null,"arrayLength":null,"arrayChildren":null}],"name":"RemoveProfile","anonymous":false},{"type":"event","inputs":[{"name":"_profiler","type":"address","baseType":"address","indexed":false,"components":null,"arrayLength":null,"arrayChildren":null},{"name":"_user","type":"address","baseType":"address","indexed":false,"components":null,"arrayLength":null,"arrayChildren":null}],"name":"SetProfile","anonymous":false},{"type":"event","inputs":[{"name":"_user","type":"address","baseType":"address","indexed":false,"components":null,"arrayLength":null,"arrayChildren":null}],"name":"Update","anonymous":false},{"type":"function","inputs":[{"name":"_user","type":"address","baseType":"address","components":null,"arrayLength":null,"arrayChildren":null}],"name":"burn","constant":false,"outputs":[],"stateMutability":"nonpayable","payable":false,"gas":null},{"type":"function","inputs":[{"name":"_user","type":"address","baseType":"address","components":null,"arrayLength":null,"arrayChildren":null}],"name":"getID","constant":true,"outputs":[{"name":"","type":"tuple","baseType":"tuple","components":[{"name":"UID","type":"bytes32","baseType":"bytes32","components":null,"arrayLength":null,"arrayChildren":null},{"name":"nameHash","type":"bytes32","baseType":"bytes32","components":null,"arrayLength":null,"arrayChildren":null},{"name":"dobHash","type":"uint256","baseType":"uint256","components":null,"arrayLength":null,"arrayChildren":null},{"name":"phone","type":"bytes32","baseType":"bytes32","components":null,"arrayLength":null,"arrayChildren":null}],"arrayLength":null,"arrayChildren":null}],"stateMutability":"view","payable":false,"gas":null},{"type":"function","inputs":[{"name":"_profiler","type":"address","baseType":"address","components":null,"arrayLength":null,"arrayChildren":null},{"name":"_user","type":"address","baseType":"address","components":null,"arrayLength":null,"arrayChildren":null}],"name":"getProfile","constant":true,"outputs":[{"name":"","type":"tuple","baseType":"tuple","components":[{"name":"entity","type":"string","baseType":"string","components":null,"arrayLength":null,"arrayChildren":null},{"name":"dataHash","type":"uint256","baseType":"uint256","components":null,"arrayLength":null,"arrayChildren":null},{"name":"timestamp","type":"uint256","baseType":"uint256","components":null,"arrayLength":null,"arrayChildren":null}],"arrayLength":null,"arrayChildren":null}],"stateMutability":"view","payable":false,"gas":null},{"type":"function","inputs":[{"name":"_user","type":"address","baseType":"address","components":null,"arrayLength":null,"arrayChildren":null}],"name":"getSoul","constant":true,"outputs":[{"name":"","type":"tuple","baseType":"tuple","components":[{"name":"UID","type":"bytes32","baseType":"bytes32","components":null,"arrayLength":null,"arrayChildren":null},{"name":"nameHash","type":"bytes32","baseType":"bytes32","components":null,"arrayLength":null,"arrayChildren":null},{"name":"dobHash","type":"uint256","baseType":"uint256","components":null,"arrayLength":null,"arrayChildren":null},{"name":"phone","type":"bytes32","baseType":"bytes32","components":null,"arrayLength":null,"arrayChildren":null}],"arrayLength":null,"arrayChildren":null}],"stateMutability":"view","payable":false,"gas":null},{"type":"function","inputs":[{"name":"_profiler","type":"address","baseType":"address","components":null,"arrayLength":null,"arrayChildren":null},{"name":"_user","type":"address","baseType":"address","components":null,"arrayLength":null,"arrayChildren":null}],"name":"hasProfile","constant":true,"outputs":[{"name":"","type":"bool","baseType":"bool","components":null,"arrayLength":null,"arrayChildren":null}],"stateMutability":"view","payable":false,"gas":null},{"type":"function","inputs":[{"name":"_user","type":"address","baseType":"address","components":null,"arrayLength":null,"arrayChildren":null}],"name":"hasSoul","constant":true,"outputs":[{"name":"","type":"bool","baseType":"bool","components":null,"arrayLength":null,"arrayChildren":null}],"stateMutability":"view","payable":false,"gas":null},{"type":"function","inputs":[{"name":"_user","type":"address","baseType":"address","components":null,"arrayLength":null,"arrayChildren":null}],"name":"listProfiles","constant":true,"outputs":[{"name":"","type":"address[]","baseType":"array","components":null,"arrayLength":-1,"arrayChildren":{"name":"","type":"address","baseType":"address","components":null,"arrayLength":null,"arrayChildren":null}}],"stateMutability":"view","payable":false,"gas":null},{"type":"function","inputs":[{"name":"_user","type":"address","baseType":"address","components":null,"arrayLength":null,"arrayChildren":null},{"name":"_identityData","type":"tuple","baseType":"tuple","components":[{"name":"UID","type":"bytes32","baseType":"bytes32","components":null,"arrayLength":null,"arrayChildren":null},{"name":"nameHash","type":"bytes32","baseType":"bytes32","components":null,"arrayLength":null,"arrayChildren":null},{"name":"dobHash","type":"uint256","baseType":"uint256","components":null,"arrayLength":null,"arrayChildren":null},{"name":"phone","type":"bytes32","baseType":"bytes32","components":null,"arrayLength":null,"arrayChildren":null}],"arrayLength":null,"arrayChildren":null}],"name":"mint","constant":false,"outputs":[],"stateMutability":"nonpayable","payable":false,"gas":null},{"type":"function","inputs":[],"name":"name","constant":true,"outputs":[{"name":"","type":"string","baseType":"string","components":null,"arrayLength":null,"arrayChildren":null}],"stateMutability":"view","payable":false,"gas":null},{"type":"function","inputs":[],"name":"owner","constant":true,"outputs":[{"name":"","type":"address","baseType":"address","components":null,"arrayLength":null,"arrayChildren":null}],"stateMutability":"view","payable":false,"gas":null},{"type":"function","inputs":[{"name":"_profiler","type":"address","baseType":"address","components":null,"arrayLength":null,"arrayChildren":null},{"name":"_user","type":"address","baseType":"address","components":null,"arrayLength":null,"arrayChildren":null}],"name":"removeProfile","constant":false,"outputs":[],"stateMutability":"nonpayable","payable":false,"gas":null},{"type":"function","inputs":[],"name":"renounceOwnership","constant":false,"outputs":[],"stateMutability":"nonpayable","payable":false,"gas":null},{"type":"function","inputs":[{"name":"_user","type":"address","baseType":"address","components":null,"arrayLength":null,"arrayChildren":null},{"name":"_profileData","type":"tuple","baseType":"tuple","components":[{"name":"entity","type":"string","baseType":"string","components":null,"arrayLength":null,"arrayChildren":null},{"name":"dataHash","type":"uint256","baseType":"uint256","components":null,"arrayLength":null,"arrayChildren":null},{"name":"timestamp","type":"uint256","baseType":"uint256","components":null,"arrayLength":null,"arrayChildren":null}],"arrayLength":null,"arrayChildren":null}],"name":"setProfile","constant":false,"outputs":[],"stateMutability":"nonpayable","payable":false,"gas":null},{"type":"function","inputs":[{"name":"newOwner","type":"address","baseType":"address","components":null,"arrayLength":null,"arrayChildren":null}],"name":"transferOwnership","constant":false,"outputs":[],"stateMutability":"nonpayable","payable":false,"gas":null},{"type":"function","inputs":[{"name":"_user","type":"address","baseType":"address","components":null,"arrayLength":null,"arrayChildren":null},{"name":"_identityData","type":"tuple","baseType":"tuple","components":[{"name":"UID","type":"bytes32","baseType":"bytes32","components":null,"arrayLength":null,"arrayChildren":null},{"name":"nameHash","type":"bytes32","baseType":"bytes32","components":null,"arrayLength":null,"arrayChildren":null},{"name":"dobHash","type":"uint256","baseType":"uint256","components":null,"arrayLength":null,"arrayChildren":null},{"name":"phone","type":"bytes32","baseType":"bytes32","components":null,"arrayLength":null,"arrayChildren":null}],"arrayLength":null,"arrayChildren":null}],"name":"update","constant":false,"outputs":[],"stateMutability":"nonpayable","payable":false,"gas":null}]